Module_Encoder.v
module encoder(
  input [3:0] A,
  input reset,
  input ready,
  output reg [3:0] S
);

  always @(posedge reset or posedge ready) begin
    if (reset) begin
      S <= 4'b0000; 
    end else if (ready) begin
      S[0] <= ~A[3] & ~A[2] & A[1] & A[0] | ~A[3] & A[2] & ~A[1] | ~A[3] & A[2] & ~A[0] | A[3] & ~A[2] & ~A[0] | A[3] & A[2] & A[1];
      S[1] <= ((~A[3] & ~A[1]) | (~A[2] & ~A[1] & ~A[0]) | (~A[3] & A[2]) | (A[3] & ~A[2] & A[1] & A[0]));
      S[2] <= ((~A[3] & ~A[0]) | (~A[2] & A[1] & A[0]) | (A[3] & A[2] & A[0]));
      S[3] <= ((A[2] & ~A[1]) | (A[2] & A[0]) | (A[3] & ~A[2] & A[1]));
    end
  end

endmodule
        
module test_bench();

  reg [3:0] A;
  reg reset;
  reg ready;
  wire [3:0] S;

  encoder uut (
    .A(A),
    .reset(reset),
    .ready(ready),
    .S(S)
  );


  initial begin
  $dumpfile("Module_encoder.vcd");
  $dumpvars(0,A, S, ready, reset );
    ready = 0;
    reset = 1;
    #10
    reset = 0; 
    ready = 0;
    #10 
    A = 4'b0000;    
    reset = 0;
    ready = 1;
    #10
    ready = 0; 
    $display("%b %b", A, S);
    reset = 1;
    #10
    reset = 0; 
    ready = 0;
    #10
    A = 4'b0001;    
    reset = 0;
    ready = 1;
    #10
    ready = 0; 
    $display("%b %b", A, S);
    reset = 1;
    #10
    reset = 0; 
    ready = 0;
    #10
    A = 4'b0010;    
    reset = 0;
    ready = 1;
    #10
    ready = 0; 
    $display("%b %b", A, S);
    reset = 1;
    #10
    reset = 0; 
    ready = 0;
    #10   
    A = 4'b0011;    
    reset = 0;
    ready = 1;
    #10
    ready = 0; 
    $display("%b %b", A, S);
    reset = 1;
    #10
    reset = 0; 
    ready = 0;
    #10   
    A = 4'b0100;    
    reset = 0;
    ready = 1;
    #10
    ready = 0; 
    $display("%b %b", A, S);
    reset = 1;
    #10
    reset = 0; 
    ready = 0;
    #10   
    A = 4'b0101;    
    reset = 0;
    ready = 1;
    #10
    ready = 0; 
    $display("%b %b", A, S);
    reset = 1;
    #10
    reset = 0; 
    ready = 0;
    #10   
    A = 4'b0110;    
    reset = 0;
    ready = 1;
    #10
    ready = 0; 
    $display("%b %b", A, S);
    reset = 1;
    #10
    reset = 0; 
    ready = 0;
    #10   
    A = 4'b0111;    
    reset = 0;
    ready = 1;
    #10
    ready = 0; 
    $display("%b %b", A, S);
    reset = 1;
    #10
    reset = 0; 
    ready = 0;
    #10   
    A = 4'b1000;    
    reset = 0;
    ready = 1;
    #10
    ready = 0; 
    $display("%b %b", A, S);
    reset = 1;
    #10
    reset = 0; 
    ready = 0;
    #10   
    A = 4'b1001;    
    reset = 0;
    ready = 1;
    #10
    ready = 0; 
    $display("%b %b", A, S);
    reset = 1;
    #10
    reset = 0; 
    ready = 0;
    #10   
    A = 4'b1010;    
    reset = 0;
    ready = 1;
    #10
    ready = 0; 
    $display("%b %b", A, S);
    reset = 1;
    #10
    reset = 0; 
    ready = 0;
    #10   
    A = 4'b1011;    
    reset = 0;
    ready = 1;
    #10
    ready = 0; 
    $display("%b %b", A, S);
    reset = 1;
    #10
    reset = 0; 
    ready = 0;
    #10   
    A = 4'b1100;    
    reset = 0;
    ready = 1;
    #10
    ready = 0; 
    $display("%b %b", A, S);
    reset = 1;
    #10
    reset = 0; 
    ready = 0;
    #10   
    A = 4'b1101;    
    reset = 0;
    ready = 1;
    #10
    ready = 0; 
    $display("%b %b", A, S);
    reset = 1;
    #10
    reset = 0; 
    ready = 0;
    #10   
    A = 4'b1110;    
    reset = 0;
    ready = 1;
    #10
    ready = 0; 
    $display("%b %b", A, S);
    reset = 1;
    #10
    reset = 0; 
    ready = 0;
    #10   
    A = 4'b1111;    
    reset = 0;
    ready = 1;
    #10
    ready = 0; 
    $display("%b %b", A, S);
    #10
    $finish;
  end

endmodule

Module_encoder.vcd
$date
	Sun Oct 08 21:21:12 2023
$end
$version
	Icarus Verilog
$end
$timescale
	1s
$end
$scope module test_bench $end
$var reg 4 ! A [3:0] $end
$upscope $end
$scope module test_bench $end
$var wire 4 " S [3:0] $end
$upscope $end
$scope module test_bench $end
$var reg 1 # ready $end
$upscope $end
$scope module test_bench $end
$var reg 1 $ reset $end
$upscope $end
$enddefinitions $end
$comment Show the parameter values. $end
$dumpall
$end
#0
$dumpvars
1$
0#
b0 "
bx !
$end
#10
0$
#20
b110 "
1#
b0 !
#30
b0 "
1$
0#
#40
0$
#50
b10 "
1#
b1 !
#60
b0 "
1$
0#
#70
0$
#80
b100 "
1#
b10 !
#90
b0 "
1$
0#
#100
0$
#110
b101 "
1#
b11 !
#120
b0 "
1$
0#
#130
0$
#140
b1111 "
1#
b100 !
#150
b0 "
1$
0#
#160
0$
#170
b1011 "
1#
b101 !
#180
b0 "
1$
0#
#190
0$
#200
b111 "
1#
b110 !
#210
b0 "
1$
0#
#220
0$
#230
b1010 "
1#
b111 !
#240
b0 "
1$
0#
#250
0$
#260
b11 "
1#
b1000 !
#270
b0 "
1$
0#
#280
0$
#290
1#
b1001 !
#300
1$
0#
#310
0$
#320
b1001 "
1#
b1010 !
#330
b0 "
1$
0#
#340
0$
#350
b1110 "
1#
b1011 !
#360
b0 "
1$
0#
#370
0$
#380
b1000 "
1#
b1100 !
#390
b0 "
1$
0#
#400
0$
#410
b1100 "
1#
b1101 !
#420
b0 "
1$
0#
#430
0$
#440
b1 "
1#
b1110 !
#450
b0 "
1$
0#
#460
0$
#470
b1101 "
1#
b1111 !
#480
0#
